robustlabs/__init__.py
robustlabs/amr.py
robustlabs/amt.py
robustlabs/api.py
robustlabs/cli.py
robustlabs/domain.py
robustlabs/evaluator.py
robustlabs/plugins.py
robustlabs/rg.py
robustlabs/web/index.html
robustlabs/web/package-lock.json
robustlabs/web/package.json
robustlabs/web/server.py
robustlabs/web/tsconfig.json
robustlabs/web/tsconfig.node.json
robustlabs/web/vite.config.ts
robustlabs/web/src/App.tsx
robustlabs/web/src/index.css
robustlabs/web/src/main.tsx
robustlabs/web/templates/dashboard.html
robustlabs-0.1.1.dist-info/METADATA
robustlabs-0.1.1.dist-info/WHEEL
robustlabs-0.1.1.dist-info/entry_points.txt
robustlabs-0.1.1.dist-info/RECORD
